{
  "_todo": {
    "address": "Real Sabaneta address pending — design placeholder in use. Brief confirms Sabaneta, exact address TBD.",
    "fresha": "Fresha link pending setup."
  },
  "meta": {
    "title": "Golden Beauty Studio — Sabaneta",
    "description": "Specialist nail studio in Sabaneta, Antioquia. Acrylic, polygel, builder gel and dipping by appointment."
  },
  "nav": {
    "items": {
      "trabajo": "Work",
      "servicios": "Services",
      "tecnicas": "Artists",
      "estudio": "Studio",
      "contacto": "Contact"
    },
    "cta": "Book a visit",
    "ctaShort": "Book"
  },
  "hero": {
    "eyebrow": "Nails Studio · Sabaneta",
    "title1": "With the golden touch,",
    "title2_em": "luxury in every detail.",
    "body": "We specialize in nails with flawless finishes and a premium experience that blends beauty, elegance and care into every appointment. -More than nails, we craft details that elevate your essence-",
    "ctaPrimary": "Book a visit",
    "ctaSecondary": "Pricing",
    "metaHours": "MON – SUN",
    "metaArea": "Sabaneta",
    "metaStatus": "Bookings open"
  },
  "lookbook": {
    "eyebrow": "Lookbook · 2026",
    "title1": "Our craft,",
    "title2_em": "for you",
    "body": "A selection of recent pieces. Each look notes the technique used and the artist's name. Tap any image to see it in detail.",
    "allLabel": "All",
    "seeAll": "See the full archive",
    "seeLess": "See less",
    "lightbox": {
      "close": "Close",
      "next": "Next",
      "previous": "Previous",
      "counter": "{current} / {total}"
    }
  },
  "servicios": {
    "eyebrow": "Menu · Prices visible",
    "title1": "What we offer,",
    "title2_em": "no fine print.",
    "body": "Listed prices and times apply to simple designs up to length #3. Other lengths, complex designs and nail art are quoted separately before your appointment.",
    "labels": {
      "from": "from",
      "currencySuffix": " COP"
    },
    "categories": {
      "montajes": {
        "label": "Builds",
        "sub": "New systems · Extension",
        "items": {
          "acrylic-sculpted":  { "name": "Sculpted acrylic",         "desc": "Perfect structure · Standout durability" },
          "polygel-sculpted":  { "name": "Sculpted polygel",         "desc": "Lightweight extension · Natural finish" },
          "polygel-dual":      { "name": "Dual-system polygel",      "desc": "Luxury precision · Flawless finish" },
          "builder-gel-dual":  { "name": "Dual-system builder gel",  "desc": "Strength · Delicacy · Perfection" },
          "press-on":          { "name": "Press-on",                 "desc": "Instant luxury · Style and comfort" }
        }
      },
      "retoques": {
        "label": "Refills",
        "sub": "System maintenance",
        "items": {
          "acrylic-refill":     { "name": "Acrylic refill",     "desc": "3 refills per build, every 21 days max" },
          "polygel-refill":     { "name": "Polygel refill",     "desc": "3 refills per build, every 21 days max" },
          "builder-gel-refill": { "name": "Builder gel refill", "desc": "3 refills per build, every 21 days max" }
        }
      },
      "forrados": {
        "label": "Overlays",
        "sub": "Reinforcement, no extension",
        "items": {
          "polygel-overlay":      { "name": "Polygel overlay",      "desc": "On the natural nail" },
          "builder-gel-overlay":  { "name": "Builder gel overlay",  "desc": "On the natural nail" },
          "acrylic-overlay":      { "name": "Acrylic overlay",      "desc": "On the natural nail" },
          "dipping":              { "name": "Dipping",              "desc": "Powder system, no monomer" },
          "rubber-base-leveling": { "name": "Rubber base leveling", "desc": "Structural base coat" }
        }
      },
      "sencillos": {
        "label": "Simple",
        "sub": "Manicure · pedicure",
        "items": {
          "semi-permanent-hands": { "name": "Semi-permanent hands", "desc": "Cleanup + gel polish" },
          "semi-permanent-feet":  { "name": "Semi-permanent feet",  "desc": "Cleanup + gel polish" },
          "hands-cleanup-only":   { "name": "Hands cleanup only",   "desc": "No polish" },
          "feet-cleanup-only":    { "name": "Feet cleanup only",    "desc": "No polish" }
        }
      },
      "extras": {
        "label": "Extras",
        "sub": "Add-on services",
        "items": {
          "system-removal":         { "name": "External system removal",      "desc": "Waived on your first visit · For nails from another salon" },
          "single-sculpted-nail":   { "name": "Single sculpted nail",         "desc": "Individual replacement · Any system" },
          "design-per-nail":        { "name": "Design / decoration per nail", "desc": "Nail art applied on top of your service" },
          "in-depth-foot-cleaning": { "name": "In-depth foot cleaning",       "desc": "Fungus, ingrown nails and special cases" }
        }
      }
    },
    "footnote": "One-week warranty on product lift (excluding charms or rhinestones).",
    "cta": "Book my appointment"
  },
  "diccionario": {
    "eyebrow": "Understanding the techniques",
    "title1": "Before you choose,",
    "title2_em": "know what you're getting.",
    "body": "Each technique has its own logic, duration and ideal nail type. A quick guide so you know what to ask for — and why.",
    "fallback": "You can also message us on WhatsApp if you'd like personal advice.",
    "labels": { "duration": "Duration", "ideal": "Best for" },
    "items": [
      { "name": "Acrylic", "dur": "3–4 weeks", "ideal": "Defined shape · structure", "body": "A mix of polymer and liquid monomer molded onto the nail. The classic system: maximum strength and sculpted shape via filing. Ideal for long extensions and architectural designs." },
      { "name": "Polygel", "dur": "3–4 weeks", "ideal": "Lightweight extension", "body": "A moldable paste-gel applied with a dual-form. Lighter than acrylic, feels natural and allows clean extensions. LED-cured — no odor. Recommended for thin nails or anyone seeking discretion." },
      { "name": "Builder gel", "dur": "3–4 weeks", "ideal": "Reinforcing the natural nail", "body": "A thick gel cured under UV/LED. A structural layer that protects the natural nail without extending it much. Polished finish, high durability and minimal wear on removal." },
      { "name": "Dipping", "dur": "2–3 weeks", "ideal": "Long-lasting wear", "body": "A manicure technique using acrylic powder for a resilient, lightweight and long-lasting finish. Ideal for strong, glossy and natural-looking nails for weeks." },
      { "name": "Semi-permanent", "dur": "2–3 weeks", "ideal": "Color on natural nails", "body": "Long-lasting gel polish cured under a UV/LED lamp. Glossy, lightweight and natural finish — keep your nails flawless from simple designs to creative nail art." },
      { "name": "Press On", "dur": "Custom", "ideal": "Ready-to-wear · events", "body": "Ready-to-wear nails that deliver a quick manicure in different shapes, lengths and custom designs, with no sculpting required." }
    ]
  },
  "tecnicas": {
    "eyebrow": "Meet the artists",
    "title1": "The difference has",
    "title2_em": "a name.",
    "team": [
      {
        "name": "Valentina M.",
        "role": "Founder · Sculpted acrylic",
        "years": "8 years",
        "quote": "Technique is learned; the eye is trained appointment by appointment."
      },
      {
        "name": "Laura R.",
        "role": "Polygel · Editorial design",
        "years": "5 years",
        "quote": "Every hand tells a different story. I just frame it."
      }
    ],
    "bookWith": "Book with"
  },
  "estudio": {
    "eyebrow": "05 · The studio",
    "title1": "A space designed for",
    "title2_em": "women who love luxury in the details.",
    "leadItalic": "Golden was born from the idea of turning personal care into an experience of comfort and exclusivity — making every woman feel confident, feminine and authentic.",
    "body1": "Our nail artists have mastered every technique we offer: choose your favorite knowing the result will always be stunning.",
    "body2": "We're based in Sabaneta, in a modern, elegant and welcoming space designed for a sophisticated and exclusive experience.",
    "stats": [
      { "n": "02h", "l": "Average duration", "s": "Per appointment, no overlap" },
      { "n": "02", "l": "Working stations", "s": "Intimate studio, not a salon" },
      { "n": "06", "l": "Techniques mastered", "s": "Built + simple" },
      { "n": "100%", "l": "Sterilized material", "s": "Opened in front of the client" }
    ],
    "hygiene": {
      "eyebrow": "Hygiene & process",
      "title1": "Your health",
      "title2_em": "is non-negotiable.",
      "intro": "What others treat as optional, we treat as essential. You'll see it every visit.",
      "items": [
        ["Sterilization", "Every tool we use is sterile."],
        ["Single use", "Every disposable item is discarded after use."],
        ["Sealed products", "Every material is opened in front of the client."],
        ["Disinfected table", "Surface and UV lamp cleaned between appointments."],
        ["Premium brands", "The best on the market, for you."],
        ["No double-booking", "We're dedicated to you until the last minute of your appointment."]
      ]
    }
  },
  "contacto": {
    "eyebrow": "06 · Visit us",
    "title1": "Find us in",
    "title2_em": "Sabaneta.",
    "address": {
      "label": "Address",
      "line1": "Calle 69 Sur #43a - 41, First Floor",
      "line2": "Sabaneta · Antioquia · Colombia",
      "line3": "Half a block from the Registraduría"
    },
    "hours": {
      "label": "Hours",
      "rows": [
        ["Mon — Sat", "09:00 — 19:00"],
        ["Sunday", "10:00 — 15:00"],
        ["Holidays", "Closed"]
      ],
      "closed": "Closed"
    },
    "ctaBook": "Book my appointment →",
    "ctaWhatsapp": "WhatsApp →",
    "socials": ["Instagram", "TikTok"],
    "map": {
      "park": "Sabaneta Park",
      "pin": "Golden · here",
      "openIn": "Open in Google Maps",
      "coords": "6.156° N · 75.617° W"
    }
  },
  "footer": {
    "tagline": "Specialist nail studio.\nSabaneta · Medellín · Antioquia.",
    "visit": {
      "title": "Visit us",
      "address1": "Calle 69 Sur #43a - 41, First Floor",
      "address2": "Sabaneta, Antioquia",
      "hours": "Mon – Sun"
    },
    "find": {
      "title": "Find us",
      "links": [
        "Instagram @goldenbeauty",
        "WhatsApp Business",
        "AgendaPro · Bookings",
        "Google Maps"
      ]
    },
    "copyright": "© 2026 Golden Beauty Studio. All rights reserved.",
    "legal": ["Privacy", "Terms"]
  },
  "floating": {
    "whatsapp": "WhatsApp",
    "cta": "Book →"
  }
}
